dexterity/__init__.py
dexterity/effector.py
dexterity/environment.py
dexterity/exception.py
dexterity/goal.py
dexterity/hints.py
dexterity/py.typed
dexterity/task.py
dexterity/task_test.py
dexterity/controllers/__init__.py
dexterity/controllers/mapper.py
dexterity/controllers/mapper_test.py
dexterity/controllers/dls/__init__.py
dexterity/controllers/dls/dls.py
dexterity/controllers/dls/dls_test.py
dexterity/effectors/__init__.py
dexterity/effectors/hand_effector.py
dexterity/effectors/hand_effector_test.py
dexterity/effectors/mujoco_actuation.py
dexterity/effectors/wrappers/__init__.py
dexterity/effectors/wrappers/base.py
dexterity/effectors/wrappers/previous_action.py
dexterity/effectors/wrappers/previous_action_test.py
dexterity/effectors/wrappers/smooth_action.py
dexterity/effectors/wrappers/smooth_action_test.py
dexterity/inverse_kinematics/__init__.py
dexterity/inverse_kinematics/ik_solver.py
dexterity/inverse_kinematics/ik_solver_test.py
dexterity/manipulation/__init__.py
dexterity/manipulation/explore.py
dexterity/manipulation/loader_test.py
dexterity/manipulation/manipulation_test.py
dexterity/manipulation/goals/__init__.py
dexterity/manipulation/goals/fingertip_position.py
dexterity/manipulation/goals/prop_orientation.py
dexterity/manipulation/props/__init__.py
dexterity/manipulation/props/target_sphere.py
dexterity/manipulation/props/juggling_ball/__init__.py
dexterity/manipulation/props/juggling_ball/juggling_ball_test.py
dexterity/manipulation/props/juggling_ball/rgby.png
dexterity/manipulation/props/openai_cube/__init__.py
dexterity/manipulation/props/openai_cube/openai_cube.png
dexterity/manipulation/props/openai_cube/openai_cube_test.py
dexterity/manipulation/shared/__init__.py
dexterity/manipulation/shared/cameras.py
dexterity/manipulation/shared/constants.py
dexterity/manipulation/shared/observations.py
dexterity/manipulation/shared/rewards.py
dexterity/manipulation/shared/tags.py
dexterity/manipulation/shared/workspaces.py
dexterity-0.0.15.dist-info/LICENSE
dexterity-0.0.15.dist-info/METADATA
dexterity-0.0.15.dist-info/WHEEL
dexterity-0.0.15.dist-info/top_level.txt
dexterity-0.0.15.dist-info/zip-safe
dexterity-0.0.15.dist-info/RECORD
