Metadata-Version: 2.1
Name: dexterity
Version: 0.0.15
Summary: Software and tasks for dexterous multi-fingered hand manipulation, powered by MuJoCo
Home-page: https://github.com/kevinzakka/dexterity
Author: Kevin Zakka
Author-email: kevinarmandzakka@gmail.com
Maintainer: Kevin Zakka
Maintainer-email: kevinarmandzakka@gmail.com
License: MIT
Classifier: Development Status :: 3 - Alpha
Classifier: Intended Audience :: Developers
Classifier: Intended Audience :: Science/Research
Classifier: License :: OSI Approved :: MIT License
Classifier: Natural Language :: English
Classifier: Programming Language :: Python :: 3
Classifier: Programming Language :: Python :: 3.7
Classifier: Programming Language :: Python :: 3.8
Classifier: Programming Language :: Python :: 3.9
Classifier: Topic :: Scientific/Engineering :: Artificial Intelligence
Requires-Python: >=3.7
License-File: LICENSE
Requires-Dist: absl-py
Requires-Dist: numpy
Requires-Dist: typing-extensions
Requires-Dist: mujoco
Requires-Dist: dm-control (>=1.0.1)
Requires-Dist: dm-robotics-geometry
Requires-Dist: dm-robotics-transformations
Provides-Extra: dev
Requires-Dist: black ; extra == 'dev'
Requires-Dist: isort ; extra == 'dev'
Requires-Dist: flake8 ; extra == 'dev'
Requires-Dist: mypy ; extra == 'dev'
Requires-Dist: ipdb ; extra == 'dev'
Requires-Dist: jupyter ; extra == 'dev'
Requires-Dist: pytest-xdist ; extra == 'dev'
Requires-Dist: matplotlib ; extra == 'dev'
Requires-Dist: imageio ; extra == 'dev'
Requires-Dist: imageio-ffmpeg ; extra == 'dev'
Provides-Extra: examples
Requires-Dist: matplotlib ; extra == 'examples'
Requires-Dist: imageio ; extra == 'examples'
Requires-Dist: imageio-ffmpeg ; extra == 'examples'
Provides-Extra: testing
Requires-Dist: pytest-xdist ; extra == 'testing'
